MANIFEST.in
README.rst
setup.py
django_yacbv.egg-info/PKG-INFO
django_yacbv.egg-info/SOURCES.txt
django_yacbv.egg-info/dependency_links.txt
django_yacbv.egg-info/not-zip-safe
django_yacbv.egg-info/requires.txt
django_yacbv.egg-info/top_level.txt
yacbv/__init__.py
yacbv/base.py