Metadata-Version: 1.1
Name: django-yacbv
Version: 0.0.1
Summary: Replacement for Django's ClassBasedView.
Home-page: https://github.com/hirokiky/django-yacbv
Author: hirokiky
Author-email: hirokiky@gmail.com
License: MIT
Platform: UNKNOWN
Classifier: Development Status :: 2 - Pre-Alpha
Classifier: Intended Audience :: Developers
Classifier: Programming Language :: Python
Classifier: Programming Language :: Python :: 3
Classifier: Programming Language :: Python :: 3.3
Classifier: Programming Language :: Python :: Implementation :: CPython
Classifier: Framework :: Django
Classifier: Topic :: Internet :: WWW/HTTP
Classifier: Topic :: Internet :: WWW/HTTP :: WSGI
Classifier: License :: OSI Approved :: MIT License
